s3_manage/__init__.py
s3_manage/s3_manage.py
s3UpManager-0.0.1.dist-info/LICENSE
s3UpManager-0.0.1.dist-info/METADATA
s3UpManager-0.0.1.dist-info/WHEEL
s3UpManager-0.0.1.dist-info/top_level.txt
s3UpManager-0.0.1.dist-info/RECORD
